{"products": {"productId": "303909", "title": "フラップバックパック", "reviewTotal": "0", "defaultColor": "69", "average": "0.0", "description": "", "material": "[68BLUE]表地:綿84%・ナイロン16%,裏地:ポリエステル100%,別布:ポリエステル100％,[その他カラ―]表地:ポリエステル100%,裏地:ポリエステル100%", "specification": "開閉方法:ファスナー開き,外ポケットあり・内ポケットあり,【サイズ】縦40×横(底)30cm,マチ:14cm,立ち上がり(持ち手):9cm", "skus": [{"sku": "303909-09-999-000", "color": "09", "size": "999"}, {"sku": "303909-68-999-000", "color": "68", "size": "999"}, {"sku": "303909-69-999-000", "color": "69", "size": "999"}], "colors": [{"name": "BLACK", "code": "09", "img": "products/303909/images/09_303909_large.jpg", "colorImg": "products/303909/images/09_303909.jpg"}, {"name": "BLUE", "code": "68", "img": "products/303909/images/68_303909_large.jpg", "colorImg": "products/303909/images/68_303909.jpg"}, {"name": "NAVY", "code": "69", "img": "products/303909/images/69_303909_large.jpg", "colorImg": "products/303909/images/69_303909.jpg"}], "sizes": [{"name": "", "code": "999"}], "reviews": [], "stylings": [{"type": "product", "image": "products/303909/images/09_303909_large.jpg", "items": []}, {"type": "product", "image": "products/303909/images/68_303909_large.jpg", "items": []}, {"type": "product", "image": "products/303909/images/69_303909_large.jpg", "items": []}, {"type": "product", "image": "products/303909/images/303909_sub2.jpg", "items": []}], "measurement": []}}