{"products": {"productId": "311551", "title": "핀 세트(도그)KJ", "reviewTotal": "0", "defaultColor": "63", "average": "0.0", "description": "핀 세트(도그)KJ", "material": ".", "specification": "", "skus": [{"sku": "311551COL32NCL999000", "color": "32", "size": "999"}, {"sku": "311551COL63NCL999000", "color": "63", "size": "999"}], "colors": [{"name": "BEIGE", "code": "32", "img": "products/311551/images_jpg/32_311551_large.jpg", "colorImg": "products/311551/images_jpg/32_311551.jpg"}, {"name": "BLUE", "code": "63", "img": "products/311551/images_jpg/63_311551_large.jpg", "colorImg": "products/311551/images_jpg/63_311551.jpg"}], "sizes": [{"name": "ONE SIZE", "code": "999"}], "reviews": [], "stylings": [{"type": "product", "image": "products/311551/images_jpg/32_311551_large.jpg", "items": []}, {"type": "product", "image": "products/311551/images_jpg/63_311551_large.jpg", "items": []}, {"type": "product", "image": "products/311551/images_jpg/311551_sub2.jpg", "items": []}], "measurement": []}}