{"products": {"productId": "307502", "title": "타이즈(60데니어)3P", "reviewTotal": "0", "defaultColor": "09", "average": "0.0", "description": "타이즈(60데니어)3P", "material": ".", "specification": "", "skus": [{"sku": "307502COL09GSM004000", "color": "09", "size": "004"}, {"sku": "307502COL09GSM005000", "color": "09", "size": "005"}], "colors": [{"name": "BLACK", "code": "09", "img": "products/307502/images_jpg/09_307502_large.jpg", "colorImg": "products/307502/images_jpg/09_307502.jpg"}], "sizes": [{"name": "M", "code": "004"}, {"name": "L", "code": "005"}], "reviews": [], "stylings": [{"type": "product", "image": "products/307502/images_jpg/09_307502_large.jpg", "items": []}, {"type": "product", "image": "products/307502/images_jpg/307502_sub2.jpg", "items": []}], "measurement": []}}