{"products": {"productId": "305278", "title": "GIRLSマドラスチェックワンピース(半袖)", "reviewTotal": "1", "defaultColor": "66", "average": "5.0", "description": "", "material": "本体:綿100%,裏地:綿100%", "specification": "前中央飾りボタン・ボタン×4,ウエスト:総ゴム入り・ゴム調節口あり,裏地あり(スカート部分)", "skus": [{"sku": "305278-66-110-000", "color": "66", "size": "110"}, {"sku": "305278-66-120-000", "color": "66", "size": "120"}, {"sku": "305278-66-130-000", "color": "66", "size": "130"}, {"sku": "305278-66-140-000", "color": "66", "size": "140"}, {"sku": "305278-66-150-000", "color": "66", "size": "150"}, {"sku": "305278-78-110-000", "color": "78", "size": "110"}, {"sku": "305278-78-120-000", "color": "78", "size": "120"}, {"sku": "305278-78-130-000", "color": "78", "size": "130"}, {"sku": "305278-78-140-000", "color": "78", "size": "140"}, {"sku": "305278-78-150-000", "color": "78", "size": "150"}], "colors": [{"name": "BLUE", "code": "66", "img": "products/305278/images/66_305278_large.jpg", "colorImg": "products/305278/images/66_305278.jpg"}, {"name": "PURPLE", "code": "78", "img": "products/305278/images/78_305278_large.jpg", "colorImg": "products/305278/images/78_305278.jpg"}], "sizes": [{"name": "110", "code": "110"}, {"name": "120", "code": "120"}, {"name": "130", "code": "130"}, {"name": "140", "code": "140"}, {"name": "150", "code": "150"}], "reviews": [{"sizeClean": "150", "sex": "女性", "age": "10代", "height": "141～150cm", "weight": "36～40kg", "rating": "None", "shoeSize": "23cm", "review": "小６の娘に買いました。チェック柄や袖が可愛らしく、涼しくて良いみたいです。", "helpful": "0", "fit": "3"}], "stylings": [{"type": "lookbook", "image": "style/23_G18SS6-g19-al-0274_180427-xxxl.jpg", "items": [{"productId": "297904", "title": "リボンスカーフヘアゴムセット", "image": "products/297904/images/09_297904_large.jpg"}, {"productId": "303257", "title": "GIRLSスポーツサンダル", "image": "products/303257/images/09_303257_large.jpg"}, {"productId": "305278", "title": "GIRLSマドラスチェックワンピース(半袖)", "image": "products/305278/images/66_305278_large.jpg"}]}, {"type": "share", "image": "style/9b666da67428f2ddab886f02ecb42a1a64395dd3f165e228.jpg", "items": []}], "measurement": [{"name": "着丈", "values": [{"size": "110", "value": "65"}, {"size": "120", "value": "71"}, {"size": "130", "value": "77"}, {"size": "140", "value": "83"}, {"size": "150", "value": "89"}]}, {"name": "肩幅", "values": [{"size": "110", "value": "24"}, {"size": "120", "value": "25"}, {"size": "130", "value": "27"}, {"size": "140", "value": "28.5"}, {"size": "150", "value": "30"}]}, {"name": "身幅", "values": [{"size": "110", "value": "30"}, {"size": "120", "value": "32"}, {"size": "130", "value": "34"}, {"size": "140", "value": "36"}, {"size": "150", "value": "38"}]}, {"name": "袖丈", "values": [{"size": "110", "value": "7"}, {"size": "120", "value": "7"}, {"size": "130", "value": "7.5"}, {"size": "140", "value": "8"}, {"size": "150", "value": "8"}]}]}}