{"products": {"productId": "294809", "title": "リボンスリッパ", "reviewTotal": "22", "defaultColor": "80", "average": "4.2", "description": "アッパーに施したリボンが目を引くトレンドのスリッパです。コーディネートにプラスするだけで今年らしいスタイルに。", "material": "[80]甲材：ポリエステル98%・レーヨン2%，底材：合成底，[その他カラー]甲材：ポリエステル100%，底材：合成底", "specification": "", "skus": [{"sku": "294809-09-003-000", "color": "09", "size": "003"}, {"sku": "294809-09-004-000", "color": "09", "size": "004"}, {"sku": "294809-09-005-000", "color": "09", "size": "005"}, {"sku": "294809-09-006-000", "color": "09", "size": "006"}, {"sku": "294809-16-003-000", "color": "16", "size": "003"}, {"sku": "294809-16-004-000", "color": "16", "size": "004"}, {"sku": "294809-16-005-000", "color": "16", "size": "005"}, {"sku": "294809-16-006-000", "color": "16", "size": "006"}, {"sku": "294809-55-003-000", "color": "55", "size": "003"}, {"sku": "294809-55-004-000", "color": "55", "size": "004"}, {"sku": "294809-55-005-000", "color": "55", "size": "005"}, {"sku": "294809-55-006-000", "color": "55", "size": "006"}, {"sku": "294809-80-003-000", "color": "80", "size": "003"}, {"sku": "294809-80-004-000", "color": "80", "size": "004"}, {"sku": "294809-80-005-000", "color": "80", "size": "005"}, {"sku": "294809-80-006-000", "color": "80", "size": "006"}], "colors": [{"name": "BLACK", "code": "09", "img": "products/294809/images/09_294809_large.jpg", "colorImg": "products/294809/images/09_294809.jpg"}, {"name": "RED", "code": "16", "img": "products/294809/images/16_294809_large.jpg", "colorImg": "products/294809/images/16_294809.jpg"}, {"name": "GREEN", "code": "55", "img": "products/294809/images/55_294809_large.jpg", "colorImg": "products/294809/images/55_294809.jpg"}, {"name": "80", "code": "80", "img": "products/294809/images/80_294809_large.jpg", "colorImg": "products/294809/images/80_294809.jpg"}], "sizes": [{"name": "S", "code": "003"}, {"name": "M", "code": "004"}, {"name": "L", "code": "005"}, {"name": "XL", "code": "006"}], "reviews": [{"sizeClean": "M", "sex": "女性", "age": "40代", "height": "151～155cm", "weight": "51～55kg", "rating": "None", "shoeSize": "23cm", "review": "甲高、幅広ですが\n全然きつくもなく大丈夫でした。\nGUさんのパンプスはなかなか合わないんですが（笑）\n今期流行りのチェックにしました。\nリボンが付いてますが\n大人可愛く履けますよ。\n色違いでブラックも買いたいです。", "helpful": "3", "fit": "3"}, {"sizeClean": "", "sex": "女性", "age": "30代", "height": "166～170cm", "weight": "", "rating": "None", "shoeSize": "24.5cm", "review": "普通に履けました。自分の場合、たまにジーユーのXLシューズがキツイことがあるので、おそらくこれは大きめの造りだと思います。\n店頭で全色確認しましたが、グレンチェックが個人的には一番高見えすると感じました。", "helpful": "1", "fit": "4"}, {"sizeClean": "L", "sex": "女性", "age": "20代", "height": "156～160cm", "weight": "51～55kg", "rating": "None", "shoeSize": "23.5cm", "review": "グレンチェックの靴が欲しくて、こちらが目にとまりました。\nシンプルな服装でもこれを履けばポイントになるし、ワイドパンツと合わせたらすごく可愛かったです！お値段以上です。\nファースリッパはLサイズ、ローファースリッパはLL、サンダルやスニーカーはMサイズ着用の23.5cmで、こちらはLがちょうどよかったです。ご参考までに☆", "helpful": "1", "fit": "3"}, {"sizeClean": "M", "sex": "女性", "age": "20代", "height": "", "weight": "", "rating": "None", "shoeSize": "23.5cm", "review": "店舗で見て一目惚れ♡\n試着するとまたすごくかわいい上に歩きやすそうだったので即買いでした！\n今年流行のグレンチェック♡今から秋口までいっぱい履きます！", "helpful": "1", "fit": "3"}, {"sizeClean": "L", "sex": "女性", "age": "20代", "height": "151～155cm", "weight": "", "rating": "None", "shoeSize": "23.5cm", "review": "普段はMサイズ がちょうど良いのですが\nこちらは少し小さめな作りになっているのか\nLサイズがちょうど良かったです 。\n \n履き心地が良く1日ショッピングしても\n疲れなかったです。\nデザインも可愛くてお気に入りの1足です。", "helpful": "1", "fit": "2"}, {"sizeClean": "M", "sex": "女性", "age": "30代", "height": "151～155cm", "weight": "", "rating": "None", "shoeSize": "23cm", "review": "グリーンのバッグと合わせたくてグリーン購入。自分の足が甲高なのかよくわかりませんでしたが、最近靴選びに悩むことを考えると、甲高幅広なのかもしれません…\nしかしこちらは歩く時も甲のリボンの部分がペロッとなって動きやすいため、歩いても痛くありません！\nぺたんこですが細いつま先が足を綺麗に見せてくれるので、いろんな服に合わせやすそうです！", "helpful": "1", "fit": "3"}, {"sizeClean": "M", "sex": "女性", "age": "", "height": "", "weight": "", "rating": "None", "shoeSize": "23.5cm", "review": "ネットで安くなったのを見て店舗へ。\n実際に見ても可愛いし迷わず購入。\n少し小さめに感じますが、ぺたんこだしかかとが出るデザインなので気にせず買いました。\n全く靴擦れもせずとっても可愛いです。", "helpful": "1", "fit": "2"}, {"sizeClean": "", "sex": "女性", "age": "30代", "height": "156～160cm", "weight": "46～50kg", "rating": "None", "shoeSize": "22.5cm", "review": "普段22.5cmで23cmだと大きいです。\n\nこちらの商品はSサイズでジャストフィット。\n厚手のくつ下を履いたら、\n若干かかとがでるかも〜？くらいでした。\n\n職場での上履きとして使用する予定で、\n黒を選びました。\n大人っぽい雰囲気で、動きやすいです。", "helpful": "1", "fit": "2"}, {"sizeClean": "M", "sex": "女性", "age": "", "height": "151～155cm", "weight": "46～50kg", "rating": "None", "shoeSize": "23.5cm", "review": "小さい小さい言われていたのでチャレンジしてみたところ、甲薄な私にはピッタリ。\n私の足はワイズD～Bというコンニャク足。\nGUの靴はガバガバで絶対履けない(履いたら足を傷めるし、体調も悪くなる)と諦め切っていたのですが。\nこれは履けます！初めてです！\n\n足裏はツルツル滑るし、ゆとりはまだあるので、つま先に薄めのジェルインソールを貼り付けたら安定が良くなりました。\nまだゆとりがあるけど、ヒールが殆ど無いので、前滑りして爪先を傷めたり指が外反・内反する心配はなし。\n歩いてみて、まだ足が泳ぐのが気になるようだったら、甲側にもハーフインソール貼り付けたら大丈夫そうだな、という感じです。\n\nなので、ワイズD前後の人は試す価値がありますよ！\n\nフェイクファーローファースリッパも同じ型なら買いだな！とウキウキしてます。", "helpful": "1", "fit": "3"}, {"sizeClean": "L", "sex": "女性", "age": "30代", "height": "156～160cm", "weight": "46～50kg", "rating": "None", "shoeSize": "23.5cm", "review": "値下げしていたので購入。店舗ではグリーンの在庫が少なかったです。 \nGUの靴は普段Mを選びますが、こちらのMだと余裕がなかったのでL購入しました。\n長く履いても足が痛くなくデザインもとてもかわいいです。\n少し硬いかな、で−1", "helpful": "1", "fit": "2"}, {"sizeClean": "L", "sex": "女性", "age": "30代", "height": "151～155cm", "weight": "46～50kg", "rating": "None", "shoeSize": "23.5cm", "review": "グリーン購入。幅広甲高のため、GUの靴は幅が狭くてLでも合わない物が多いのですが、こちらは他のパンプスなどに比べると広めなのか、Lで大丈夫でした。ただ、生地が硬いので一日中歩き回るような時は辛いかも。4〜5時間なら平気でした。何にでも合うのでヘビロテしてます。グレンチェックも欲しいなー！", "helpful": "0", "fit": "2"}], "stylings": [{"type": "share", "image": "style/249b3a93051d4063261197849473da12cb27e0c4d71c5040.jpg", "items": []}, {"type": "share", "image": "style/8fd4015570c47983933e12775312a90ee51c792a56ca25a5.jpg", "items": []}, {"type": "share", "image": "style/b843064d26e6e79f58d5480b14226485bdb44d799dfa3c04.jpg", "items": []}, {"type": "share", "image": "style/ba13547e6b5f889f200657034146117a28aff8ae5f147f9b.jpg", "items": []}, {"type": "share", "image": "style/7017fc9bc516cd0b18ec537f8cbfbffc1941e021b7b45654.jpg", "items": []}, {"type": "share", "image": "style/a3527a136a0314bc35a910fb618ba611324611305db853a7.jpg", "items": []}, {"type": "share", "image": "style/426a09521089e8ec69059358bbd274e9a17722bd1bd20f47.jpg", "items": []}, {"type": "share", "image": "style/6ead6fa055ab2f9c377cc8cb49d6eadff82ee718214ade18.jpg", "items": []}, {"type": "share", "image": "style/4aa48cf3ed477d8fa0b5f466cbe495bd35bf5765e8e47424.jpg", "items": []}, {"type": "share", "image": "style/44b9afba89e86b12430c7b9f6378bb0e2faab7ed9739172f.jpg", "items": []}], "measurement": [{"name": "対応サイズ", "values": [{"size": "S", "value": "22.5"}, {"size": "M", "value": "23.5"}, {"size": "L", "value": "24.5"}, {"size": "XL", "value": "25"}]}, {"name": "底幅", "values": [{"size": "S", "value": "7"}, {"size": "M", "value": "7.5"}, {"size": "L", "value": "7.5"}, {"size": "XL", "value": "8"}]}, {"name": "足囲", "values": [{"size": "S", "value": "19.5"}, {"size": "M", "value": "20"}, {"size": "L", "value": "21"}, {"size": "XL", "value": "21.5"}]}, {"name": "足長", "values": [{"size": "S", "value": "24.5"}, {"size": "M", "value": "25.5"}, {"size": "L", "value": "26.5"}, {"size": "XL", "value": "27"}]}]}}