{"products": {"productId": "290998", "title": "ウエストリボンフレアスカート", "reviewTotal": "53", "defaultColor": "19", "average": "4.6", "description": "微起毛加工を施したハリ感のある素材のフレアスカートです。後ろウエスト部分はゴムでイージーなはき心地。タックとギャザーによる軽やかなフレアシルエットが女性らしい一枚です。共地のサッシュベルトが着こなしのアクセントに。秋らしい豊富なカラー展開も魅力的です。", "material": "ポリエステル57%・綿33%・ナイロン10%", "specification": "ウエスト：後ろゴム入り(調節不可)・リボン付き(取り外し可)・ベルトループあり", "skus": [{"sku": "290998-09-003-000", "color": "09", "size": "003"}, {"sku": "290998-09-004-000", "color": "09", "size": "004"}, {"sku": "290998-09-005-000", "color": "09", "size": "005"}, {"sku": "290998-09-006-000", "color": "09", "size": "006"}, {"sku": "290998-11-003-000", "color": "11", "size": "003"}, {"sku": "290998-11-004-000", "color": "11", "size": "004"}, {"sku": "290998-11-005-000", "color": "11", "size": "005"}, {"sku": "290998-11-006-000", "color": "11", "size": "006"}, {"sku": "290998-19-003-000", "color": "19", "size": "003"}, {"sku": "290998-19-004-000", "color": "19", "size": "004"}, {"sku": "290998-19-005-000", "color": "19", "size": "005"}, {"sku": "290998-19-006-000", "color": "19", "size": "006"}, {"sku": "290998-47-003-000", "color": "47", "size": "003"}, {"sku": "290998-47-004-000", "color": "47", "size": "004"}, {"sku": "290998-47-005-000", "color": "47", "size": "005"}, {"sku": "290998-47-006-000", "color": "47", "size": "006"}, {"sku": "290998-57-003-000", "color": "57", "size": "003"}, {"sku": "290998-57-004-000", "color": "57", "size": "004"}, {"sku": "290998-57-005-000", "color": "57", "size": "005"}, {"sku": "290998-57-006-000", "color": "57", "size": "006"}, {"sku": "290998-69-003-000", "color": "69", "size": "003"}, {"sku": "290998-69-004-000", "color": "69", "size": "004"}, {"sku": "290998-69-005-000", "color": "69", "size": "005"}, {"sku": "290998-69-006-000", "color": "69", "size": "006"}, {"sku": "290998-77-003-000", "color": "77", "size": "003"}, {"sku": "290998-77-004-000", "color": "77", "size": "004"}, {"sku": "290998-77-005-000", "color": "77", "size": "005"}, {"sku": "290998-77-006-000", "color": "77", "size": "006"}], "colors": [{"name": "BLACK", "code": "09", "img": "products/290998/images_jpg/09_290998_large.jpg", "colorImg": "products/290998/images_jpg/09_290998.jpg"}, {"name": "PINK", "code": "11", "img": "products/290998/images_jpg/11_290998_large.jpg", "colorImg": "products/290998/images_jpg/11_290998.jpg"}, {"name": "WINE", "code": "19", "img": "products/290998/images_jpg/19_290998_large.jpg", "colorImg": "products/290998/images_jpg/19_290998.jpg"}, {"name": "YELLOW", "code": "47", "img": "products/290998/images_jpg/47_290998_large.jpg", "colorImg": "products/290998/images_jpg/47_290998.jpg"}, {"name": "OLIVE", "code": "57", "img": "products/290998/images_jpg/57_290998_large.jpg", "colorImg": "products/290998/images_jpg/57_290998.jpg"}, {"name": "NAVY", "code": "69", "img": "products/290998/images_jpg/69_290998_large.jpg", "colorImg": "products/290998/images_jpg/69_290998.jpg"}, {"name": "PURPLE", "code": "77", "img": "products/290998/images_jpg/77_290998_large.jpg", "colorImg": "products/290998/images_jpg/77_290998.jpg"}], "sizes": [{"name": "S", "code": "003"}, {"name": "M", "code": "004"}, {"name": "L", "code": "005"}, {"name": "XL", "code": "006"}], "reviews": [{"sizeClean": "M", "sex": "女性", "age": "30代", "height": "141～150cm", "weight": "46～50kg", "rating": "None", "shoeSize": "22.5cm", "review": "長めのフレアスカートでカーキ色を探していてこのスカートを発見！すぐに店頭へ向かいました。\nしっとりとした生地で色も濃いカーキ色ですごく可愛い！私の背が低いのでミディ丈になりいい感じ。リボンで気になるお腹も隠れるので優秀アイテムになりそうです＾＾", "helpful": "9", "fit": "3"}, {"sizeClean": "S", "sex": "女性", "age": "30代", "height": "156～160cm", "weight": "41～45kg", "rating": "None", "shoeSize": "23cm", "review": "秋色がほしくて試着したところ、丈も質感も良いです。\n広がりすぎずフワッとしていて、とてもかわいいです。", "helpful": "8", "fit": "3"}, {"sizeClean": "M", "sex": "女性", "age": "", "height": "161～165cm", "weight": "46～50kg", "rating": "None", "shoeSize": "23cm", "review": "花柄のリボンベルトスカート同様、裏地が欲しかったです。\n裏地があれば★5でした。\n\n", "helpful": "5", "fit": "3"}, {"sizeClean": "M", "sex": "女性", "age": "30代", "height": "151～155cm", "weight": "41～45kg", "rating": "None", "shoeSize": "22.5cm", "review": "いつもSサイズを買うのですが、この商品はゴムが伸びないのかちょっときつめで、トップスインにできなそうな感じだったので、Mサイズを購入しました。\nボルドーを買いましたが秋らしい色で気に入りました。\n", "helpful": "3", "fit": "2"}, {"sizeClean": "M", "sex": "女性", "age": "40代", "height": "151～155cm", "weight": "41～45kg", "rating": "None", "shoeSize": "23cm", "review": "普段XS〜Sサイズですが、こちらはウトウトのゴムがきつめなのかSではお腹が少し苦しい感じがしたので、これから厚手のニットなどインする事を考えてMサイズにしました。\nフレア感がとても可愛く丈もいい感じです。気に入ってイエローとブラックを買いました。生地もしっとりで素敵。安くて良い買い物できました。", "helpful": "3", "fit": "3"}, {"sizeClean": "L", "sex": "女性", "age": "30代", "height": "156～160cm", "weight": "51～55kg", "rating": "None", "shoeSize": "", "review": "ゆったり着たかったのでＬサイズ、ワイン色を購入致しました。結構長いですね、Mにしとけばよかったかなと思いました。\n生地は薄めで裏地も無し。真冬は着れないので完全に秋用ですね。でも落ち着いた色味が気に入ったのでたくさん着たいと思います。", "helpful": "3", "fit": "4"}, {"sizeClean": "XL", "sex": "女性", "age": "40代", "height": "151～155cm", "weight": "", "rating": "None", "shoeSize": "23cm", "review": "オリーブのXLをオンラインストアで注文いたしました。このスカートすごく欲しくてずっと探したのですが、オンラインで見つけたときあってホッとしました。ブラック、ピンク、ワイン、ネイビーも購入させて頂く予定でございます。オリーブのLが欲しかったのですがXLが最後の1枚でしたのであって良かったです。ベルトのところにリボンがついていて可愛いなぁと感じました。いつもスカートはジーユーさんのしか買わないのでリーズナブルな金額で買えるのがすごく嬉しいです。勤務先や外出するのに欠かせられないスカートに仕上がっています。このスカートの花柄のスカートも欲しくなりました。ありがとうございます。", "helpful": "2", "fit": "3"}, {"sizeClean": "M", "sex": "女性", "age": "20代", "height": "156～160cm", "weight": "36～40kg", "rating": "None", "shoeSize": "23cm", "review": "いつもスカートはSサイズを買いますがこの商品はMサイズでちょうどよかったです。", "helpful": "2", "fit": "3"}, {"sizeClean": "S", "sex": "女性", "age": "40代", "height": "151～155cm", "weight": "", "rating": "None", "shoeSize": "22.5cm", "review": "オンラインにてネイビーを購入。\n黒に近いネイビーでした。\nベルト通しが短めなのでリボンは半分に折らないと通りません。\n夏に購入したカラースカートが低身長でも何とか着こなせたので期待していたのですが、こちらは丈が少し長くバランスが取りにくい。\n残念ながら今回は返品します。", "helpful": "1", "fit": "4"}, {"sizeClean": "XL", "sex": "女性", "age": "", "height": "", "weight": "", "rating": "None", "shoeSize": "", "review": "ワイン色を購入。\n生地がしっかりしていて、裏地がなくても透けることなく良いです。\n真夏以外の季節オールマイティーに着られそうです。\nベルトあり、なしで着られるので応用範囲大です。\n形もきれいです。", "helpful": "1", "fit": "3"}, {"sizeClean": "XL", "sex": "女性", "age": "40代", "height": "151～155cm", "weight": "", "rating": "None", "shoeSize": "23cm", "review": "このスカートのイエローがLでネイビーとパープルのXLをオンラインストアで注文いたしました。以前にワイン、ピンク、オリーブを\n購入させて頂いた時とっても気にいってしまい、パープル、ネイビー、イエロー、ブラックも欲しくなりました。ブラックも購入させて頂く予定でございます。このスカートにリボンがついていて可愛いです。勤務先や外出するのに欠かせられないスカートに仕上がっています。長さも丁度良く膝が隠れるのがとても気にいっています。新色にパープルとイエローも加わって全色欲しくなりました。", "helpful": "1", "fit": "3"}], "stylings": [{"type": "share", "image": "style_jpg/90490c7813c71c0fc75c1e7d96b632cd08e415d2a6a4627c.jpg", "items": []}, {"type": "share", "image": "style_jpg/be269bdd47baf9aeb94e2ef660dcb979d23ebb7e59d1a639.jpg", "items": []}, {"type": "share", "image": "style_jpg/8a1de2f590bb2066c0b60c871b80b9a56684fb48052597e1.jpg", "items": []}, {"type": "share", "image": "style_jpg/ce6e562f1cc718f48ec1444c50f5cab64567b0dc631356aa.jpg", "items": []}, {"type": "share", "image": "style_jpg/9f6289a0917d191714f6e01720de020354bf1050ab29c30e.jpg", "items": []}, {"type": "share", "image": "style_jpg/9b1ff297bdf7de68f908ba267c45d37dc0760451e042e05c.jpg", "items": []}, {"type": "share", "image": "style_jpg/560fc39904b0aafe5cee36af922b702205b15f779b8ed427.jpg", "items": []}, {"type": "share", "image": "style_jpg/86aed62caa889a8c1706f589ebbaebb9ae4c390d71af4378.jpg", "items": []}, {"type": "share", "image": "style_jpg/43800d14b692146659bfa7986529cdff5583ed7c3911319f.jpg", "items": []}, {"type": "share", "image": "style_jpg/83a5e8a23a2797f87e8668fc0689e5ab09539ff896d99a06.jpg", "items": []}], "measurement": [{"name": "ウエスト（ヌード寸法）", "values": [{"size": "S", "value": "58〜64"}, {"size": "M", "value": "62〜68"}, {"size": "L", "value": "66〜72"}, {"size": "XL", "value": "70〜76"}]}, {"name": "スカート丈", "values": [{"size": "S", "value": "71"}, {"size": "M", "value": "71"}, {"size": "L", "value": "72"}, {"size": "XL", "value": "73"}]}]}}