{"products": {"productId": "303554", "title": "ポケ付きタンクトップ", "reviewTotal": "0", "defaultColor": "63", "average": "0.0", "description": "", "material": "綿100%", "specification": "ポケット:胸×1(左),裾:サイドスリットあり", "skus": [{"sku": "303554-09-110-000", "color": "09", "size": "110"}, {"sku": "303554-09-120-000", "color": "09", "size": "120"}, {"sku": "303554-09-130-000", "color": "09", "size": "130"}, {"sku": "303554-09-140-000", "color": "09", "size": "140"}, {"sku": "303554-09-150-000", "color": "09", "size": "150"}, {"sku": "303554-24-110-000", "color": "24", "size": "110"}, {"sku": "303554-24-120-000", "color": "24", "size": "120"}, {"sku": "303554-24-130-000", "color": "24", "size": "130"}, {"sku": "303554-24-140-000", "color": "24", "size": "140"}, {"sku": "303554-24-150-000", "color": "24", "size": "150"}, {"sku": "303554-63-110-000", "color": "63", "size": "110"}, {"sku": "303554-63-120-000", "color": "63", "size": "120"}, {"sku": "303554-63-130-000", "color": "63", "size": "130"}, {"sku": "303554-63-140-000", "color": "63", "size": "140"}, {"sku": "303554-63-150-000", "color": "63", "size": "150"}], "colors": [{"name": "BLACK", "code": "09", "img": "products/303554/images/09_303554_large.jpg", "colorImg": "products/303554/images/09_303554.jpg"}, {"name": "ORANGE", "code": "24", "img": "products/303554/images/24_303554_large.jpg", "colorImg": "products/303554/images/24_303554.jpg"}, {"name": "BLUE", "code": "63", "img": "products/303554/images/63_303554_large.jpg", "colorImg": "products/303554/images/63_303554.jpg"}], "sizes": [{"name": "110", "code": "110"}, {"name": "120", "code": "120"}, {"name": "130", "code": "130"}, {"name": "140", "code": "140"}, {"name": "150", "code": "150"}], "reviews": [], "stylings": [{"type": "lookbook", "image": "style/10_G18SS6-b13-eh-1198_180525-xxxl.jpg", "items": [{"productId": "296405", "title": "ベルクロスポーツサンダル", "image": "products/296405/images/57_296405_large.jpg"}, {"productId": "298817", "title": "チェックイージーハーフパンツ", "image": "products/298817/images/24_298817_large.jpg"}, {"productId": "303554", "title": "ポケ付きタンクトップ", "image": "products/303554/images/63_303554_large.jpg"}]}], "measurement": [{"name": "身丈", "values": [{"size": "110", "value": "43"}, {"size": "120", "value": "46"}, {"size": "130", "value": "49"}, {"size": "140", "value": "52"}, {"size": "150", "value": "55"}]}, {"name": "身幅", "values": [{"size": "110", "value": "33"}, {"size": "120", "value": "35"}, {"size": "130", "value": "37"}, {"size": "140", "value": "39"}, {"size": "150", "value": "41"}]}]}}