{"products": {"productId": "306633", "title": "GIRLSショートソックス2PC", "reviewTotal": "0", "defaultColor": "80", "average": "0.0", "description": "", "material": "(CHECK)ポリエステル91%・綿7%・ポリウレタン2%,(STRIPE)ポリエステル90%・綿8%・ポリウレタン2%", "specification": "", "skus": [{"sku": "306633-80-003-000", "color": "80", "size": "003"}, {"sku": "306633-80-004-000", "color": "80", "size": "004"}], "colors": [{"name": "80", "code": "80", "img": "products/306633/images/80_306633_large.jpg", "colorImg": "products/306633/images/80_306633.jpg"}], "sizes": [{"name": "16-21cm", "code": "003"}, {"name": "21-24cm", "code": "004"}], "reviews": [], "stylings": [{"type": "lookbook", "image": "style/03_0530MAMA14203_180727_180727-xxxl.jpg", "items": [{"productId": "304917", "title": "GIRLSサロペットワイドパンツ", "image": "products/304917/images/60_304917_large.jpg"}, {"productId": "305011", "title": "GIRLSスラブフロントノットT(半袖)", "image": "products/305011/images/24_305011_large.jpg"}, {"productId": "305028", "title": "GIRLSフェイクファーサンダル", "image": "products/305028/images/31_305028_large.jpg"}, {"productId": "305908", "title": "コーデュロイターバン", "image": "products/305908/images/69_305908_large.jpg"}, {"productId": "306633", "title": "GIRLSショートソックス2PC", "image": "products/306633/images/80_306633_large.jpg"}]}], "measurement": [{"name": "対応サイズ", "values": [{"size": "16-21", "value": "16〜21"}, {"size": "21-24", "value": "21〜24"}, {"size": "16-21", "value": "16〜21"}, {"size": "21-24", "value": "21〜24"}]}]}}