{"products": {"productId": "307478", "title": "쇼트 삭스3P(컬러)", "reviewTotal": "0", "defaultColor": "90", "average": "0.0", "description": "쇼트 삭스3P(컬러)", "material": ".", "specification": "", "skus": [{"sku": "307478COL90NCL999000", "color": "90", "size": "999"}], "colors": [{"name": "", "code": "90", "img": "products/307478/images_jpg/90_307478_large.jpg", "colorImg": "products/307478/images_jpg/90_307478.jpg"}], "sizes": [{"name": "ONE SIZE", "code": "999"}], "reviews": [], "stylings": [{"type": "product", "image": "products/307478/images_jpg/90_307478_large.jpg", "items": []}, {"type": "product", "image": "products/307478/images_jpg/307478_sub2.jpg", "items": []}], "measurement": []}}