{"products": {"productId": "307476", "title": "커버 삭스3PA(논슬립)", "reviewTotal": "0", "defaultColor": "09", "average": "0.0", "description": "발등 길이가 짧은 타입의 커버 삭스입니다. 3켤레 세트로 세탁이 용이합니다. 일상에서 사용하는데 추천하는 아이템입니다.", "material": "폴리에스터73%·면18%·폴리우레탄5%·나일론4%", "specification": "", "skus": [{"sku": "307476COL09NCL999000", "color": "09", "size": "999"}, {"sku": "307476COL90NCL999000", "color": "90", "size": "999"}], "colors": [{"name": "09 BLACK", "code": "09", "img": "products/307476/images/09_307476_large.jpg", "colorImg": "products/307476/images/09_307476.jpg"}, {"name": "90", "code": "90", "img": "products/307476/images/90_307476_large.jpg", "colorImg": "products/307476/images/90_307476.jpg"}], "sizes": [{"name": "ONE SIZE", "code": "999"}], "reviews": [], "stylings": [{"type": "product", "image": "products/307476/images/09_307476_large.jpg", "items": []}, {"type": "product", "image": "products/307476/images/90_307476_large.jpg", "items": []}, {"type": "product", "image": "products/307476/images/307476_sub2.jpg", "items": []}], "measurement": []}}