{"products": {"productId": "296380", "title": "GIRLSサイドスリットチュニック(半袖)", "reviewTotal": "4", "defaultColor": "69", "average": "4.2", "description": "", "material": "綿100%", "specification": "裾:サイドスリットあり", "skus": [{"sku": "296380-01-110-000", "color": "01", "size": "110"}, {"sku": "296380-01-120-000", "color": "01", "size": "120"}, {"sku": "296380-01-130-000", "color": "01", "size": "130"}, {"sku": "296380-01-140-000", "color": "01", "size": "140"}, {"sku": "296380-01-150-000", "color": "01", "size": "150"}, {"sku": "296380-48-110-000", "color": "48", "size": "110"}, {"sku": "296380-48-120-000", "color": "48", "size": "120"}, {"sku": "296380-48-130-000", "color": "48", "size": "130"}, {"sku": "296380-48-140-000", "color": "48", "size": "140"}, {"sku": "296380-48-150-000", "color": "48", "size": "150"}, {"sku": "296380-69-110-000", "color": "69", "size": "110"}, {"sku": "296380-69-120-000", "color": "69", "size": "120"}, {"sku": "296380-69-130-000", "color": "69", "size": "130"}, {"sku": "296380-69-140-000", "color": "69", "size": "140"}, {"sku": "296380-69-150-000", "color": "69", "size": "150"}], "colors": [{"name": "OFF WHITE", "code": "01", "img": "products/296380/images_jpg/01_296380_large.jpg", "colorImg": "products/296380/images_jpg/01_296380.jpg"}, {"name": "YELLOW", "code": "48", "img": "products/296380/images_jpg/48_296380_large.jpg", "colorImg": "products/296380/images_jpg/48_296380.jpg"}, {"name": "NAVY", "code": "69", "img": "products/296380/images_jpg/69_296380_large.jpg", "colorImg": "products/296380/images_jpg/69_296380.jpg"}], "sizes": [{"name": "110", "code": "110"}, {"name": "120", "code": "120"}, {"name": "130", "code": "130"}, {"name": "140", "code": "140"}, {"name": "150", "code": "150"}], "reviews": [{"sizeClean": "150", "sex": "女性", "age": "10代", "height": "141～150cm", "weight": "", "rating": "None", "shoeSize": "", "review": "イエローを購入。\nモデルさんと同じように黒のレギンスパンツを合わせましたが、デニムのレギパンも爽やかで可愛かったです。\nもうすぐキッズ商品サイズアウトしてしまいます。\nユニクロさんと同じく、ネット限定でも良いので 160cmサイズを作って欲しいです！！", "helpful": "0", "fit": "3"}, {"sizeClean": "130", "sex": "女性", "age": "30代", "height": "111～120cm", "weight": "16～20kg", "rating": "None", "shoeSize": "", "review": "120センチの娘に130を購入。やや大きいですが、気にならない程度。ポケットがないのでやめようかな、と思いましたが、あまりの可愛さに負けて購入しました。夏は暑くてレギンスを嫌がるのですが、これに合わせるためには履く！と本人も言ってるので。990円で購入しましたが今見たら590円に！！ちょっとショックなので星四つ。", "helpful": "0", "fit": "4"}, {"sizeClean": "", "sex": "女性", "age": "", "height": "", "weight": "", "rating": "None", "shoeSize": "", "review": "時々、子ども用でとても可愛いものを見つけます。しかし、残念ながら・当然のことながらサイズが合いません。これの大人サイズがあったら買っています。背丈はいいのに、幅が子ども用では収まらない自分が恨めしい。", "helpful": "0", "fit": "3"}, {"sizeClean": "", "sex": "女性", "age": "", "height": "", "weight": "", "rating": "None", "shoeSize": "", "review": "白を購入しましたが透けます。シャツに付いている小さなリボンまでハッキリ見えてしまうので真っ白なシャツでないと着せれません。フワッとしたデザインなので横に広がり太って見えてポッチャリの我が子には似合わなく残念でした。", "helpful": "0", "fit": "4"}], "stylings": [{"type": "product", "image": "products/296380/images_jpg/01_296380_large.jpg", "items": []}, {"type": "product", "image": "products/296380/images_jpg/48_296380_large.jpg", "items": []}, {"type": "product", "image": "products/296380/images_jpg/69_296380_large.jpg", "items": []}, {"type": "product", "image": "products/296380/images_jpg/296380_sub2.jpg", "items": []}], "measurement": [{"name": "着丈", "values": [{"size": "110", "value": "55.5"}, {"size": "120", "value": "60"}, {"size": "130", "value": "64.5"}, {"size": "140", "value": "69"}, {"size": "150", "value": "73.5"}]}, {"name": "身幅", "values": [{"size": "110", "value": "27"}, {"size": "120", "value": "28.5"}, {"size": "130", "value": "30"}, {"size": "140", "value": "31.5"}, {"size": "150", "value": "33"}]}]}}