{"products": {"productId": "290285", "title": "キャンバススニーカー", "reviewTotal": "4", "defaultColor": "69", "average": "5.0", "description": "キャンバス生地を使用したスニーカー。シンプルなデザインは、さまざまなコーディネートで活躍してくれるのでオススメです。", "material": "甲材：綿100%，底材：合成底", "specification": "", "skus": [{"sku": "290285-01-003-000", "color": "01", "size": "003"}, {"sku": "290285-01-004-000", "color": "01", "size": "004"}, {"sku": "290285-01-005-000", "color": "01", "size": "005"}, {"sku": "290285-01-006-000", "color": "01", "size": "006"}, {"sku": "290285-09-003-000", "color": "09", "size": "003"}, {"sku": "290285-09-004-000", "color": "09", "size": "004"}, {"sku": "290285-09-005-000", "color": "09", "size": "005"}, {"sku": "290285-09-006-000", "color": "09", "size": "006"}, {"sku": "290285-11-003-000", "color": "11", "size": "003"}, {"sku": "290285-11-004-000", "color": "11", "size": "004"}, {"sku": "290285-11-005-000", "color": "11", "size": "005"}, {"sku": "290285-11-006-000", "color": "11", "size": "006"}, {"sku": "290285-69-003-000", "color": "69", "size": "003"}, {"sku": "290285-69-004-000", "color": "69", "size": "004"}, {"sku": "290285-69-005-000", "color": "69", "size": "005"}, {"sku": "290285-69-006-000", "color": "69", "size": "006"}], "colors": [{"name": "OFF WHITE", "code": "01", "img": "products/290285/images/01_290285_large.jpg", "colorImg": "products/290285/images/01_290285.jpg"}, {"name": "BLACK", "code": "09", "img": "products/290285/images/09_290285_large.jpg", "colorImg": "products/290285/images/09_290285.jpg"}, {"name": "PINK", "code": "11", "img": "products/290285/images/11_290285_large.jpg", "colorImg": "products/290285/images/11_290285.jpg"}, {"name": "NAVY", "code": "69", "img": "products/290285/images/69_290285_large.jpg", "colorImg": "products/290285/images/69_290285.jpg"}], "sizes": [{"name": "S", "code": "003"}, {"name": "M", "code": "004"}, {"name": "L", "code": "005"}, {"name": "XL", "code": "006"}], "reviews": [{"sizeClean": "L", "sex": "女性", "age": "30代", "height": "156～160cm", "weight": "", "rating": "None", "shoeSize": "24cm", "review": "白のLを購入。\n前回買いそびれたのですが、新作のこちの商品の方が高見えしてたので即購入しました。\n買って大満足！！\n白はトレンドだし軽やかに見えるのでこれからも大活躍間違いなしです。\n\nMは歩くと辛い感じだったのでLにしましたが、1番売れてるのか、2足で完売しそうでした。\nどんな服にでもコーデしやすいです。\nオススメです(*'ω' *)", "helpful": "0", "fit": "4"}, {"sizeClean": "L", "sex": "女性", "age": "20代", "height": "151～155cm", "weight": "46～50kg", "rating": "None", "shoeSize": "24.5cm", "review": "安いしデザインがかわいい\n何にでも合わせやすいし気にいっています。\n", "helpful": "0", "fit": "3"}, {"sizeClean": "", "sex": "女性", "age": "", "height": "", "weight": "", "rating": "None", "shoeSize": "", "review": "白のXLを購入しました。楽に履くことができるので、マメの心配はなさそうです。大人になって初めて白いスニーカーを買いたいと思わせてくれた商品です。スカンツに合わせていますが、いい感じです。買ってよかった！", "helpful": "0", "fit": "4"}, {"sizeClean": "M", "sex": "女性", "age": "10代", "height": "156～160cm", "weight": "", "rating": "None", "shoeSize": "23.5cm", "review": "紺の靴を購入しました。\nシンプルでどんな服にも合わせやすいです。", "helpful": "0", "fit": "3"}], "stylings": [{"type": "share", "image": "style/7ac2156ad0b9c7a3452067ea20c0fccbb511e0e842e8d4fa.jpg", "items": []}, {"type": "share", "image": "style/2b74e175e2e42c70584ad10f5314c7e6e47ef4b159451707.jpg", "items": []}], "measurement": [{"name": "対応サイズ", "values": [{"size": "S", "value": "22.5"}, {"size": "M", "value": "23.5"}, {"size": "L", "value": "24.5"}, {"size": "XL", "value": "25"}]}, {"name": "底幅", "values": [{"size": "S", "value": "7.5"}, {"size": "M", "value": "8"}, {"size": "L", "value": "8"}, {"size": "XL", "value": "8.5"}]}, {"name": "足囲", "values": [{"size": "S", "value": "21"}, {"size": "M", "value": "21.5"}, {"size": "L", "value": "22.5"}, {"size": "XL", "value": "22.5"}]}, {"name": "足長", "values": [{"size": "S", "value": "23"}, {"size": "M", "value": "24"}, {"size": "L", "value": "25"}, {"size": "XL", "value": "25.5"}]}]}}