{"products": {"productId": "297057", "title": "ヘビーウェイトT(5分袖)", "reviewTotal": "18", "defaultColor": "72", "average": "4.4", "description": "しっかりとしたカットソー素材を使用したヘビーウェイトTシャツ。ボトムスを選ばないシンプルなシルエットの万能アイテムなので、ロングシーズン着用できます。（XS,XXLサイズは、オンラインストアのみでの販売となります。）", "material": "[03GRAY]綿94%・レーヨン6%,[その他カラー]綿100%", "specification": "ポケット:胸×1(左),裾:サイドスリットあり", "skus": [{"sku": "297057-01-002-000", "color": "01", "size": "002"}, {"sku": "297057-01-003-000", "color": "01", "size": "003"}, {"sku": "297057-01-004-000", "color": "01", "size": "004"}, {"sku": "297057-01-005-000", "color": "01", "size": "005"}, {"sku": "297057-01-006-000", "color": "01", "size": "006"}, {"sku": "297057-01-007-000", "color": "01", "size": "007"}, {"sku": "297057-03-002-000", "color": "03", "size": "002"}, {"sku": "297057-03-003-000", "color": "03", "size": "003"}, {"sku": "297057-03-004-000", "color": "03", "size": "004"}, {"sku": "297057-03-005-000", "color": "03", "size": "005"}, {"sku": "297057-03-006-000", "color": "03", "size": "006"}, {"sku": "297057-03-007-000", "color": "03", "size": "007"}, {"sku": "297057-09-002-000", "color": "09", "size": "002"}, {"sku": "297057-09-003-000", "color": "09", "size": "003"}, {"sku": "297057-09-004-000", "color": "09", "size": "004"}, {"sku": "297057-09-005-000", "color": "09", "size": "005"}, {"sku": "297057-09-006-000", "color": "09", "size": "006"}, {"sku": "297057-09-007-000", "color": "09", "size": "007"}, {"sku": "297057-12-002-000", "color": "12", "size": "002"}, {"sku": "297057-12-003-000", "color": "12", "size": "003"}, {"sku": "297057-12-004-000", "color": "12", "size": "004"}, {"sku": "297057-12-005-000", "color": "12", "size": "005"}, {"sku": "297057-12-006-000", "color": "12", "size": "006"}, {"sku": "297057-12-007-000", "color": "12", "size": "007"}, {"sku": "297057-16-002-000", "color": "16", "size": "002"}, {"sku": "297057-16-003-000", "color": "16", "size": "003"}, {"sku": "297057-16-004-000", "color": "16", "size": "004"}, {"sku": "297057-16-005-000", "color": "16", "size": "005"}, {"sku": "297057-16-006-000", "color": "16", "size": "006"}, {"sku": "297057-16-007-000", "color": "16", "size": "007"}, {"sku": "297057-36-002-000", "color": "36", "size": "002"}, {"sku": "297057-36-003-000", "color": "36", "size": "003"}, {"sku": "297057-36-004-000", "color": "36", "size": "004"}, {"sku": "297057-36-005-000", "color": "36", "size": "005"}, {"sku": "297057-36-006-000", "color": "36", "size": "006"}, {"sku": "297057-36-007-000", "color": "36", "size": "007"}, {"sku": "297057-46-002-000", "color": "46", "size": "002"}, {"sku": "297057-46-003-000", "color": "46", "size": "003"}, {"sku": "297057-46-004-000", "color": "46", "size": "004"}, {"sku": "297057-46-005-000", "color": "46", "size": "005"}, {"sku": "297057-46-006-000", "color": "46", "size": "006"}, {"sku": "297057-46-007-000", "color": "46", "size": "007"}, {"sku": "297057-69-002-000", "color": "69", "size": "002"}, {"sku": "297057-69-003-000", "color": "69", "size": "003"}, {"sku": "297057-69-004-000", "color": "69", "size": "004"}, {"sku": "297057-69-005-000", "color": "69", "size": "005"}, {"sku": "297057-69-006-000", "color": "69", "size": "006"}, {"sku": "297057-69-007-000", "color": "69", "size": "007"}, {"sku": "297057-72-002-000", "color": "72", "size": "002"}, {"sku": "297057-72-003-000", "color": "72", "size": "003"}, {"sku": "297057-72-004-000", "color": "72", "size": "004"}, {"sku": "297057-72-005-000", "color": "72", "size": "005"}, {"sku": "297057-72-006-000", "color": "72", "size": "006"}, {"sku": "297057-72-007-000", "color": "72", "size": "007"}], "colors": [{"name": "OFF WHITE", "code": "01", "img": "products/297057/images_jpg/01_297057_large.jpg", "colorImg": "products/297057/images_jpg/01_297057.jpg"}, {"name": "GRAY", "code": "03", "img": "products/297057/images_jpg/03_297057_large.jpg", "colorImg": "products/297057/images_jpg/03_297057.jpg"}, {"name": "BLACK", "code": "09", "img": "products/297057/images_jpg/09_297057_large.jpg", "colorImg": "products/297057/images_jpg/09_297057.jpg"}, {"name": "PINK", "code": "12", "img": "products/297057/images_jpg/12_297057_large.jpg", "colorImg": "products/297057/images_jpg/12_297057.jpg"}, {"name": "RED", "code": "16", "img": "products/297057/images_jpg/16_297057_large.jpg", "colorImg": "products/297057/images_jpg/16_297057.jpg"}, {"name": "BROWN", "code": "36", "img": "products/297057/images_jpg/36_297057_large.jpg", "colorImg": "products/297057/images_jpg/36_297057.jpg"}, {"name": "YELLOW", "code": "46", "img": "products/297057/images_jpg/46_297057_large.jpg", "colorImg": "products/297057/images_jpg/46_297057.jpg"}, {"name": "NAVY", "code": "69", "img": "products/297057/images_jpg/69_297057_large.jpg", "colorImg": "products/297057/images_jpg/69_297057.jpg"}, {"name": "PURPLE", "code": "72", "img": "products/297057/images_jpg/72_297057_large.jpg", "colorImg": "products/297057/images_jpg/72_297057.jpg"}], "sizes": [{"name": "XS", "code": "002"}, {"name": "S", "code": "003"}, {"name": "M", "code": "004"}, {"name": "L", "code": "005"}, {"name": "XL", "code": "006"}, {"name": "XXL", "code": "007"}], "reviews": [{"sizeClean": "S", "sex": "女性", "age": "30代", "height": "151～155cm", "weight": "36～40kg", "rating": "None", "shoeSize": "22cm未満", "review": "白黒グレーを3色買いしました、レーススカートに合わせてスポーツミックスでもジーンズに合わせても良くてラフ感がすごく気に入りました。普段XS着用ですがSでもきれます。普段Mの、母もSをきられるデザインだったので、2人で着よういうことで買いました！ボディラインがぴったり出るようなデザインではないのでお腹らへんが気になる母がとても喜んでいます笑", "helpful": "0", "fit": "3"}, {"sizeClean": "M", "sex": "女性", "age": "40代", "height": "161～165cm", "weight": "51～55kg", "rating": "None", "shoeSize": "", "review": "これ去年買いました。\n生地が厚めなので真夏には着れないです。\n丈が短めで、身幅があり、スキニーとバランスがいいです。", "helpful": "0", "fit": "4"}, {"sizeClean": "L", "sex": "女性", "age": "40代", "height": "161～165cm", "weight": "46～50kg", "rating": "None", "shoeSize": "", "review": "大きめで着たいのでLにしました。普段着用に白黒グレーの3色買いました。ワイドパンツはもちろん、テーパードのチノパンやスキニーデニムにも合わせやすいです。", "helpful": "0", "fit": "4"}, {"sizeClean": "M", "sex": "女性", "age": "", "height": "", "weight": "", "rating": "None", "shoeSize": "", "review": "ジャストサイズで着たいのでMサイズを購入。厚手なので夏は着れないですが形もいいしヘビロテ間違いないです", "helpful": "0", "fit": "3"}, {"sizeClean": "S", "sex": "女性", "age": "30代", "height": "156～160cm", "weight": "56～60kg", "rating": "None", "shoeSize": "24cm", "review": "MかSで迷いましたが、試着をしてSを購入。カラーはブラウンとホワイトを選びました。\nいつもMかLを選ぶのですが、こちらの商品はゆったり目に作られているので、Sでもまだゆとりがある位でした。オーバーな感じで着用したかったのですが、程よい感じが気に入っています。Mサイズより上だとせっかくのショート感がなくなってしまう感じでした。", "helpful": "0", "fit": "4"}, {"sizeClean": "", "sex": "女性", "age": "20代", "height": "156～160cm", "weight": "", "rating": "None", "shoeSize": "", "review": "白を購入したのですがとっても可愛くて着やすかったです！別の色もほしくなりました(^^)", "helpful": "0", "fit": "3"}, {"sizeClean": "XL", "sex": "女性", "age": "30代", "height": "161～165cm", "weight": "71～75kg", "rating": "None", "shoeSize": "25.5cm", "review": "私は太めですがビッグサイズでゆったり着れます。去年もGUで似たようなのを買い使えたので今年も購入しました。", "helpful": "0", "fit": "5"}, {"sizeClean": "L", "sex": "女性", "age": "50代", "height": "156～160cm", "weight": "51～55kg", "rating": "None", "shoeSize": "24.5cm", "review": "白を購入しました！\n形も綺麗で着やすいです。\n黒も購入したかったのですが売り切れでした。\n残念です。", "helpful": "0", "fit": "3"}, {"sizeClean": "L", "sex": "女性", "age": "40代", "height": "161～165cm", "weight": "", "rating": "None", "shoeSize": "", "review": "去年も同じものを購入しましたが、着倒したので今年も購入しました。\n白、黒、ネイビー購入しましたが、安いのでもう一枚ずつ買い足す予定です。\n普段Lサイズですが、こちらのLサイズは少し大きめです。ゆったり着るにはいいかと思います。\n生地がぶ厚めですが、真夏でもちょうどいいと思います！", "helpful": "0", "fit": "3"}, {"sizeClean": "L", "sex": "女性", "age": "30代", "height": "", "weight": "", "rating": "None", "shoeSize": "", "review": "デブで、いつも服には悩みます\nそしてこれからの季節暑いのでどうしようかまさます迷います\n\nそこで汗を吸い取る素材で、かつ体型もカバーしてくれるこちらのシャツを見つけ即買い！\n\nいいですね！\n夏でも着ますよ〜\nイロチ買いするつもりです！", "helpful": "0", "fit": "4"}, {"sizeClean": "L", "sex": "女性", "age": "20代", "height": "171～175cm", "weight": "", "rating": "None", "shoeSize": "", "review": "オレンジ？を購入しました。私は身長があるのですがLサイズでも十分なサイズ感でゆったりきられます。生地もしっかりしているので夏でもブラトップやキャミソールなしで着られます。デニムに合わせたらすごい可愛いかったです。", "helpful": "0", "fit": "4"}], "stylings": [{"type": "share", "image": "style_jpg/963bb6d73de42438803c8a259ffc93f9095721168ef638c5.jpg", "items": []}, {"type": "share", "image": "style_jpg/b6139b362a27b4cc49676c22add15073a428931edbcb0be5.jpg", "items": []}, {"type": "share", "image": "style_jpg/4cdc50ea5d7368a0e8a1abe3b0a1fd8bc77c68780d01030d.jpg", "items": []}, {"type": "share", "image": "style_jpg/b8baabe4f9d05e1e94634cceda39f512b863f2d2b4c8e3a2.jpg", "items": []}, {"type": "share", "image": "style_jpg/d3eff64a7d9d243c9e7efbbb4cddd144c3cca596aa386a2b.jpg", "items": []}, {"type": "share", "image": "style_jpg/a76056142e64bed60b2db3c396e6befa723cb73d7ea791be.jpg", "items": []}, {"type": "share", "image": "style_jpg/d1a2ed28c0fbb8fa618f278fa3e40bb45ab83d052ece3c3a.jpg", "items": []}, {"type": "share", "image": "style_jpg/e3458068a3075ce377fc4c6a9adb8289423782a43e10463e.jpg", "items": []}], "measurement": [{"name": "身丈", "values": [{"size": "XS", "value": "53.5"}, {"size": "S", "value": "53.5"}, {"size": "M", "value": "55"}, {"size": "L", "value": "57.5"}, {"size": "XL", "value": "59"}, {"size": "XXL", "value": "59"}]}, {"name": "肩幅", "values": [{"size": "XS", "value": "51.5"}, {"size": "S", "value": "53.5"}, {"size": "M", "value": "56"}, {"size": "L", "value": "59"}, {"size": "XL", "value": "62"}, {"size": "XXL", "value": "63.5"}]}, {"name": "身幅", "values": [{"size": "XS", "value": "48.5"}, {"size": "S", "value": "50.5"}, {"size": "M", "value": "53"}, {"size": "L", "value": "56"}, {"size": "XL", "value": "59"}, {"size": "XXL", "value": "60.5"}]}, {"name": "袖丈", "values": [{"size": "XS", "value": "17"}, {"size": "S", "value": "17"}, {"size": "M", "value": "17"}, {"size": "L", "value": "17.5"}, {"size": "XL", "value": "17.5"}, {"size": "XXL", "value": "17.5"}]}]}}