{"products": {"productId": "305211", "title": "복서 쇼츠3P", "reviewTotal": "0", "defaultColor": "91", "average": "0.0", "description": "복서 쇼츠3P", "material": ".", "specification": "", "skus": [{"sku": "305211COL80GML004000", "color": "80", "size": "004"}, {"sku": "305211COL80GML005000", "color": "80", "size": "005"}, {"sku": "305211COL81GML004000", "color": "81", "size": "004"}, {"sku": "305211COL81GML005000", "color": "81", "size": "005"}, {"sku": "305211COL82GML004000", "color": "82", "size": "004"}, {"sku": "305211COL82GML005000", "color": "82", "size": "005"}, {"sku": "305211COL90GML004000", "color": "90", "size": "004"}, {"sku": "305211COL90GML005000", "color": "90", "size": "005"}, {"sku": "305211COL91GML004000", "color": "91", "size": "004"}, {"sku": "305211COL91GML005000", "color": "91", "size": "005"}], "colors": [{"name": "", "code": "80", "img": "products/305211/images_jpg/80_305211_large.jpg", "colorImg": "products/305211/images_jpg/80_305211.jpg"}, {"name": "", "code": "81", "img": "products/305211/images_jpg/81_305211_large.jpg", "colorImg": "products/305211/images_jpg/81_305211.jpg"}, {"name": "", "code": "82", "img": "products/305211/images_jpg/82_305211_large.jpg", "colorImg": "products/305211/images_jpg/82_305211.jpg"}, {"name": "", "code": "90", "img": "products/305211/images_jpg/90_305211_large.jpg", "colorImg": "products/305211/images_jpg/90_305211.jpg"}, {"name": "", "code": "91", "img": "products/305211/images_jpg/91_305211_large.jpg", "colorImg": "products/305211/images_jpg/91_305211.jpg"}], "sizes": [{"name": "M", "code": "004"}, {"name": "L", "code": "005"}], "reviews": [], "stylings": [{"type": "product", "image": "products/305211/images_jpg/80_305211_large.jpg", "items": []}, {"type": "product", "image": "products/305211/images_jpg/81_305211_large.jpg", "items": []}, {"type": "product", "image": "products/305211/images_jpg/82_305211_large.jpg", "items": []}, {"type": "product", "image": "products/305211/images_jpg/90_305211_large.jpg", "items": []}, {"type": "product", "image": "products/305211/images_jpg/91_305211_large.jpg", "items": []}, {"type": "product", "image": "products/305211/images_jpg/305211_sub2.jpg", "items": []}], "measurement": [{"name": "엉덩이 (누드 사이즈)", "values": [{"size": "M", "value": "86〜92"}, {"size": "L", "value": "90〜96"}, {"size": "M", "value": "86〜92"}, {"size": "L", "value": "90〜96"}]}, {"name": "前丈（クロッチ部分含まず）", "values": [{"size": "M", "value": "11.5"}, {"size": "L", "value": "13"}, {"size": "M", "value": "11.5"}, {"size": "L", "value": "13"}]}]}}