{"products": {"productId": "305651", "title": "スクエアバレエシューズ", "reviewTotal": "1", "defaultColor": "80", "average": "5.0", "description": "", "material": "甲材:[80]ポリエステル65%・レーヨン35%,[その他カラー]ポリエステル100%,底材:合成底", "specification": "", "skus": [{"sku": "305651-09-003-000", "color": "09", "size": "003"}, {"sku": "305651-09-004-000", "color": "09", "size": "004"}, {"sku": "305651-09-005-000", "color": "09", "size": "005"}, {"sku": "305651-09-006-000", "color": "09", "size": "006"}, {"sku": "305651-19-003-000", "color": "19", "size": "003"}, {"sku": "305651-19-004-000", "color": "19", "size": "004"}, {"sku": "305651-19-005-000", "color": "19", "size": "005"}, {"sku": "305651-19-006-000", "color": "19", "size": "006"}, {"sku": "305651-80-003-000", "color": "80", "size": "003"}, {"sku": "305651-80-004-000", "color": "80", "size": "004"}, {"sku": "305651-80-005-000", "color": "80", "size": "005"}, {"sku": "305651-80-006-000", "color": "80", "size": "006"}], "colors": [{"name": "BLACK", "code": "09", "img": "products/305651/images_jpg/09_305651_large.jpg", "colorImg": "products/305651/images_jpg/09_305651.jpg"}, {"name": "WINE", "code": "19", "img": "products/305651/images_jpg/19_305651_large.jpg", "colorImg": "products/305651/images_jpg/19_305651.jpg"}, {"name": "80", "code": "80", "img": "products/305651/images_jpg/80_305651_large.jpg", "colorImg": "products/305651/images_jpg/80_305651.jpg"}], "sizes": [{"name": "S", "code": "003"}, {"name": "M", "code": "004"}, {"name": "L", "code": "005"}, {"name": "XL", "code": "006"}], "reviews": [{"sizeClean": "M", "sex": "女性", "age": "", "height": "161～165cm", "weight": "46～50kg", "rating": "None", "shoeSize": "23.5cm", "review": "ラウンドタイプのように足囲が狭いかと思っていましたが、ポインテッドタイプとほぼ同じ足囲でした。\n外反母趾で歩き方も悪いため、ポインテッドタイプだとつま先がすぐに傷んでしまって困っていたところに登場したこのタイプ、大変履きやすいです。\n定番化、カラー・素材バリエーションの追加、そして何より通常店でも購入できるようにしてほしいです。", "helpful": "0", "fit": "3"}], "stylings": [{"type": "product", "image": "products/305651/images_jpg/09_305651_large.jpg", "items": []}, {"type": "product", "image": "products/305651/images_jpg/19_305651_large.jpg", "items": []}, {"type": "product", "image": "products/305651/images_jpg/80_305651_large.jpg", "items": []}, {"type": "product", "image": "products/305651/images_jpg/305651_sub2.jpg", "items": []}], "measurement": [{"name": "対応サイズ", "values": [{"size": "S", "value": "22.5"}, {"size": "M", "value": "23.5"}, {"size": "L", "value": "24.5"}, {"size": "XL", "value": "25"}]}, {"name": "底幅", "values": [{"size": "S", "value": "7.3"}, {"size": "M", "value": "7.6"}, {"size": "L", "value": "7.9"}, {"size": "XL", "value": "8.1"}]}, {"name": "足囲", "values": [{"size": "S", "value": "19.6"}, {"size": "M", "value": "20.3"}, {"size": "L", "value": "21"}, {"size": "XL", "value": "21.4"}]}, {"name": "足長", "values": [{"size": "S", "value": "23.6"}, {"size": "M", "value": "24.6"}, {"size": "L", "value": "25.6"}, {"size": "XL", "value": "26.1"}]}]}}