{"products": {"productId": "297433", "title": "ショートソックス3P", "reviewTotal": "2", "defaultColor": "09", "average": "4.5", "description": "お得なショート丈ソックス3足組。消臭機能を備えた実用的なアイテムです。バリエーションが豊富なのも魅力。", "material": "[00WHITE]ポリエステル72%・綿26%・ポリウレタン2%，[09BLACK]ポリエステル74%・綿24%・ポリウレタン2%，[80](GRAY/BLACK)ポリエステル74%・綿24%・ポリウレタン2%，(NAVY)ポリエステル71%・綿27%・ポリウレタン2%", "specification": "【対応サイズ】25～27cm", "skus": [{"sku": "297433-00-999-000", "color": "00", "size": "999"}, {"sku": "297433-09-999-000", "color": "09", "size": "999"}, {"sku": "297433-80-999-000", "color": "80", "size": "999"}], "colors": [{"name": "WHITE", "code": "00", "img": "products/297433/images/00_297433_large.jpg", "colorImg": "products/297433/images/00_297433.jpg"}, {"name": "BLACK", "code": "09", "img": "products/297433/images/09_297433_large.jpg", "colorImg": "products/297433/images/09_297433.jpg"}, {"name": "80", "code": "80", "img": "products/297433/images/80_297433_large.jpg", "colorImg": "products/297433/images/80_297433.jpg"}], "sizes": [{"name": "", "code": "999"}], "reviews": [{"sizeClean": "26", "sex": "男性", "age": "10代", "height": "166～170cm", "weight": "41～45kg", "rating": "None", "shoeSize": "25.5cm", "review": "生地が暑いので部活に最適です。安いのにしっかりしてます。", "helpful": "0", "fit": "3"}, {"sizeClean": "", "sex": "女性", "age": "40代", "height": "", "weight": "", "rating": "None", "shoeSize": "", "review": "主人に頼まれて購入しました。が、真夏にこのソックスは厚いです。いくら丈が短くても、地が厚いため、不向きです。せめて涼しくなってから履くようにした方が良いです。モノは良いと思いますので、購入時期に関係なく、履く時期を選べば良いと思いました。", "helpful": "0", "fit": "4"}], "stylings": [{"type": "product", "image": "products/297433/images/00_297433_large.jpg", "items": []}, {"type": "product", "image": "products/297433/images/09_297433_large.jpg", "items": []}, {"type": "product", "image": "products/297433/images/80_297433_large.jpg", "items": []}, {"type": "product", "image": "products/297433/images/297433_sub2.jpg", "items": []}], "measurement": []}}